gh_data_utils/__init__.py
gh_data_utils/data_visualization.py
gh_data_utils/stat_tests.py
gh_data_utils-0.0.1.dist-info/LICENSE
gh_data_utils-0.0.1.dist-info/METADATA
gh_data_utils-0.0.1.dist-info/WHEEL
gh_data_utils-0.0.1.dist-info/top_level.txt
gh_data_utils-0.0.1.dist-info/RECORD
