Metadata-Version: 2.1
Name: gh-data-utils
Version: 0.0.1
Summary: A set of utilities for running and evaluating experiments at Greenhouse. Primarily designed to install in a Mode Analytics Python notebook.
Home-page: https://github.com/grnhse/gh-data-utils
Author: Greenhouse Data Science Team
Author-email: data-team@greenhouse.io
License: UNKNOWN
Platform: UNKNOWN
Classifier: Programming Language :: Python :: 3
Classifier: License :: OSI Approved :: MIT License
Classifier: Operating System :: OS Independent
Requires-Python: >=3.6
